{
  "tabPane": [
    {
      "title": "SmartDashboard",
      "autoPopulate": true,
      "autoPopulatePrefix": "SmartDashboard/",
      "widgetPane": {
        "gridSize": 128.0,
        "showGrid": true,
        "hgap": 16.0,
        "vgap": 16.0,
        "titleType": 0,
        "tiles": {
          "5,0": {
            "size": [
              1,
              1
            ],
            "content": {
              "_type": "Text View",
              "_source0": "network_table:///SmartDashboard/TunableNumbers/Shelf Angle",
              "_title": "TunableNumbers/Shelf Angle",
              "_glyph": 148,
              "_showGlyph": false
            }
          },
          "6,0": {
            "size": [
              1,
              1
            ],
            "content": {
              "_type": "Text View",
              "_source0": "network_table:///SmartDashboard/TunableNumbers/Ground Extension",
              "_title": "TunableNumbers/Ground Extension",
              "_glyph": 148,
              "_showGlyph": false
            }
          },
          "7,0": {
            "size": [
              1,
              1
            ],
            "content": {
              "_type": "Text View",
              "_source0": "network_table:///SmartDashboard/TunableNumbers/Hybrid Extension",
              "_title": "TunableNumbers/Hybrid Extension",
              "_glyph": 148,
              "_showGlyph": false
            }
          },
          "8,0": {
            "size": [
              1,
              1
            ],
            "content": {
              "_type": "Text View",
              "_source0": "network_table:///SmartDashboard/TunableNumbers/Mid Extension",
              "_title": "TunableNumbers/Mid Extension",
              "_glyph": 148,
              "_showGlyph": false
            }
          },
          "5,1": {
            "size": [
              1,
              1
            ],
            "content": {
              "_type": "Boolean Box",
              "_source0": "network_table:///SmartDashboard/Is Connected",
              "_title": "Is Connected",
              "_glyph": 148,
              "_showGlyph": false,
              "Colors/Color when true": "#7CFC00FF",
              "Colors/Color when false": "#8B0000FF"
            }
          },
          "6,1": {
            "size": [
              1,
              1
            ],
            "content": {
              "_type": "Text View",
              "_source0": "network_table:///SmartDashboard/ACTUAL GYRO ANGLE",
              "_title": "ACTUAL GYRO ANGLE",
              "_glyph": 148,
              "_showGlyph": false
            }
          },
          "7,1": {
            "size": [
              1,
              1
            ],
            "content": {
              "_type": "Boolean Box",
              "_source0": "network_table:///SmartDashboard/Balanced",
              "_title": "Balanced",
              "_glyph": 148,
              "_showGlyph": false,
              "Colors/Color when true": "#7CFC00FF",
              "Colors/Color when false": "#8B0000FF"
            }
          },
          "8,1": {
            "size": [
              1,
              1
            ],
            "content": {
              "_type": "Text View",
              "_source0": "network_table:///SmartDashboard/FAKE GYRO ANGLE",
              "_title": "FAKE GYRO ANGLE",
              "_glyph": 148,
              "_showGlyph": false
            }
          },
          "5,2": {
            "size": [
              1,
              1
            ],
            "content": {
              "_type": "ComboBox Chooser",
              "_source0": "network_table:///SmartDashboard/Select Auto",
              "_title": "Select Auto",
              "_glyph": 148,
              "_showGlyph": false
            }
          },
          "6,2": {
            "size": [
              1,
              1
            ],
            "content": {
              "_type": "Boolean Box",
              "_source0": "network_table:///SmartDashboard/Elevator Limit Switch",
              "_title": "Elevator Limit Switch",
              "_glyph": 148,
              "_showGlyph": false,
              "Colors/Color when true": "#7CFC00FF",
              "Colors/Color when false": "#8B0000FF"
            }
          },
          "7,2": {
            "size": [
              1,
              1
            ],
            "content": {
              "_type": "Boolean Box",
              "_source0": "network_table:///SmartDashboard/Winch Limit Switch",
              "_title": "Winch Limit Switch",
              "_glyph": 148,
              "_showGlyph": false,
              "Colors/Color when true": "#7CFC00FF",
              "Colors/Color when false": "#8B0000FF"
            }
          },
          "8,2": {
            "size": [
              1,
              1
            ],
            "content": {
              "_type": "Text View",
              "_source0": "network_table:///SmartDashboard/Substation distance",
              "_title": "Substation distance",
              "_glyph": 148,
              "_showGlyph": false
            }
          },
          "0,0": {
            "size": [
              3,
              2
            ],
            "content": {
              "_type": "Camera Stream",
              "_source0": "camera_server://photonvision_Port_1181_MJPEG_Server",
              "_title": "photonvision_Port_1181_MJPEG_Server",
              "_glyph": 148,
              "_showGlyph": false,
              "Crosshair/Show crosshair": true,
              "Crosshair/Crosshair color": "#FFFFFFFF",
              "Controls/Show controls": true,
              "Controls/Rotation": "NONE",
              "compression": -1.0,
              "fps": -1,
              "imageWidth": 0,
              "imageHeight": 0
            }
          }
        }
      }
    },
    {
      "title": "LiveWindow",
      "autoPopulate": true,
      "autoPopulatePrefix": "LiveWindow/",
      "widgetPane": {
        "gridSize": 128.0,
        "showGrid": true,
        "hgap": 16.0,
        "vgap": 16.0,
        "titleType": 0,
        "tiles": {}
      }
    },
    {
      "title": "Tab 3",
      "autoPopulate": false,
      "autoPopulatePrefix": "",
      "widgetPane": {
        "gridSize": 128.0,
        "showGrid": true,
        "hgap": 16.0,
        "vgap": 16.0,
        "titleType": 0,
        "tiles": {
          "2,0": {
            "size": [
              3,
              3
            ],
            "content": {
              "_type": "Text View",
              "_source0": "network_table:///SmartDashboard/ACTUAL GYRO ANGLE",
              "_title": "SmartDashboard/ACTUAL GYRO ANGLE",
              "_glyph": 148,
              "_showGlyph": false
            }
          },
          "5,0": {
            "size": [
              3,
              3
            ],
            "content": {
              "_type": "Text View",
              "_source0": "network_table:///SmartDashboard/FAKE GYRO ANGLE",
              "_title": "SmartDashboard/FAKE GYRO ANGLE",
              "_glyph": 148,
              "_showGlyph": false
            }
          },
          "0,0": {
            "size": [
              2,
              2
            ],
            "content": {
              "_type": "Boolean Box",
              "_source0": "network_table:///SmartDashboard/Driving up",
              "_title": "/SmartDashboard/Driving up",
              "_glyph": 148,
              "_showGlyph": false,
              "Colors/Color when true": "#7CFC00FF",
              "Colors/Color when false": "#8B0000FF"
            }
          },
          "8,0": {
            "size": [
              1,
              1
            ],
            "content": {
              "_type": "Boolean Box",
              "_source0": "network_table:///SmartDashboard/Is Connected",
              "_title": "SmartDashboard/Is Connected",
              "_glyph": 148,
              "_showGlyph": false,
              "Colors/Color when true": "#7CFC00FF",
              "Colors/Color when false": "#8B0000FF"
            }
          }
        }
      }
    }
  ],
  "windowGeometry": {
    "x": -8.0,
    "y": -8.0,
    "width": 1382.0,
    "height": 744.0
  }
}